rfcctl/__init__.py
rfcctl/context.py
rfcctl/data/__init__.py
rfcctl/data/contexts.py
rfcctl/data/rfcs.py
rfcctl/data/skeleton.py
rfcctl/main.py
rfcctl/parser.py
rfcctl/rfc.py
rfcctl-0.1.1.dist-info/LICENSE
rfcctl-0.1.1.dist-info/WHEEL
rfcctl-0.1.1.dist-info/entry_points.txt
rfcctl-0.1.1.dist-info/METADATA
rfcctl-0.1.1.dist-info/RECORD
