Metadata-Version: 2.1
Name: rfcctl
Version: 0.1.1
Summary: RFC like documents management tool
Home-page: https://github.com/SiLeader/rfcctl
License: Apache-2.0
Keywords: document
Author: SiLeader
Author-email: sileader.dev@gmail.com
Requires-Python: >=3.9,<4.0
Classifier: Development Status :: 4 - Beta
Classifier: Environment :: Console
Classifier: License :: OSI Approved :: Apache Software License
Classifier: Operating System :: OS Independent
Classifier: Programming Language :: Python :: 3
Classifier: Programming Language :: Python :: 3.9
Classifier: Programming Language :: Python :: 3.10
Classifier: Programming Language :: Python :: 3.11
Classifier: Programming Language :: Python :: 3
Classifier: Programming Language :: Python :: 3 :: Only
Classifier: Topic :: Documentation
Classifier: Topic :: Utilities
Requires-Dist: jinja2 (>=3.1.2,<4.0.0)
Project-URL: Repository, https://github.com/SiLeader/rfcctl
